README.md
setup.py
movingclusterlib/__init__.py
movingclusterlib/gates.py
movingclusterlib/graph_analyzer.py
movingclusterlib.egg-info/PKG-INFO
movingclusterlib.egg-info/SOURCES.txt
movingclusterlib.egg-info/dependency_links.txt
movingclusterlib.egg-info/not-zip-safe
movingclusterlib.egg-info/requires.txt
movingclusterlib.egg-info/top_level.txt