Metadata-Version: 2.1
Name: movingclusterlib
Version: 0.1.2
Summary: UNKNOWN
Home-page: UNKNOWN
Author: Alexander Khlebushchev
License: MIT
Platform: UNKNOWN
